src/memory.v
module dff_8bit (
    input wire clk,
    input wire rst,
    input wire en,
    input [7:0] d,
    output reg [7:0] q
);
    always @ (posedge clk or negedge rst) begin
        if (!rst)
            q <= 8'b0;
        else if (en)
            q <= d;
    end
endmodule

module fp4_fft_memory_dff (
    input wire clk,
    input wire rst,
    input wire bank_sel,
    
    //port 0: read from processing bank
    input wire [4:0] rd_addr_0,
    output wire [7:0] rd_data_0,
    
    //port 1: write to filling bank (ping-pong)
    input wire wr_en_1,
    input wire [4:0] wr_addr_1,
    input wire [7:0] wr_data_1
);

    reg [7:0] bank0_mem [0:31];
    reg [7:0] bank1_mem [0:31];

    integer i;
    
    //write logic: port 1 writes to opposite bank of bank_sel
    always @(posedge clk or negedge rst) begin
        if (!rst) begin
            for (i = 0; i < 32; i = i + 1) begin
                bank0_mem[i] <= 8'b0;
                bank1_mem[i] <= 8'b0;
            end
        end else begin
            if (wr_en_1) begin
                if (bank_sel) begin
                    //bank_sel=1: reading from bank1, so write to bank0
                    bank0_mem[wr_addr_1] <= wr_data_1;
                end else begin
                    //bank_sel=0: reading from bank0, so write to bank1
                    bank1_mem[wr_addr_1] <= wr_data_1;
                end
            end
        end
    end

    //read logic: port 0 reads from same bank as bank_sel
    assign rd_data_0 = bank_sel ? bank1_mem[rd_addr_0] : bank0_mem[rd_addr_0];

endmodule


//alternative memory implementation without dffs (using reg arrays)
//commented out as we're using dff-based design for fp4 fft

// module fp4_fft_memory (
//     input wire clk,
//     input wire rst,
    
//     //bank select line: bank 0 and bank 1
//     input wire bank_sel,

//     //read ports
//     // each bank has 32 8-bit words, with [0:3] representing real part and [4:7] representing imaginary part
//     //port 0
//     input wire [4:0] rd_addr_0, 
//     output wire [7:0] rd_data_0, 

//     input wire wr_en_0,
//     input wire [4:0] wr_addr_0,
//     input wire [7:0] wr_data_0,

//     //port 1
//     input wire [4:0] rd_addr_1,
//     output wire [7:0] rd_data_1,

//     input wire wr_en_1,
//     input wire [4:0] wr_addr_1,
//     input wire [7:0] wr_data_1,

//     input wire swap_banks // new signal to swap banks
// );

//     //memory bank: 32 x 8 bit registers, with real and imaginary support
//     reg [3:0] bank0_mem_real [0:31]; //bank 0 real part
//     reg [3:0] bank0_mem_imag [0:31]; //bank 0 imaginary part

//     reg [3:0] bank1_mem_real [0:31]; //bank 1 real part
//     reg [3:0] bank1_mem_imag [0:31]; //bank 1 imaginary part

//     //internal signals for bank selection
//     wire read_from_0, write_to_1;

//     assign read_from_0 = ~bank_sel; // Read 0 when sel is 0
//     assign write_to_1 = ~bank_sel;  // Write 1 when sel is 0 (Inverse of read)

//     //read logic for dual port read
//     always @ (posedge clk or negedge rst) begin
//         if (!rst) begin
//             rd_data_0 <= 8'b0;
//             rd_data_1 <= 8'b0;
//         end else begin
//             //port 0 read
//             if (read_from_0) begin //if bank_sel is 0 read from bank0
//                 rd_data_0[3:0] <= bank0_mem_real[rd_addr_0]; //real part of bank0 
//                 rd_data_0[7:4] <= bank0_mem_imag[rd_addr_0]; //imaginary part of bank0
//             end else begin //if bank_sel is 1 read from bank1
//                 rd_data_0[3:0] <= bank1_mem_real[rd_addr_0]; //real part of bank1
//                 rd_data_0[7:4] <= bank1_mem_imag[rd_addr_0]; //imaginary part of bank1
//             end

//             //port 1 read
//             if (read_from_0) begin //if bank_sel is 0 read from bank0
//                 rd_data_1[3:0] <= bank0_mem_real[rd_addr_1];
//                 rd_data_1[7:4] <= bank0_mem_imag[rd_addr_1];
//             end else begin //if bank_sel is 1 read from bank1
//                 rd_data_1[3:0] <= bank1_mem_real[rd_addr_1];
//                 rd_data_1[7:4] <= bank1_mem_imag[rd_addr_1];
//             end
//         end
//     end

//     //write logic for dual port write
//     always @ (posedge clk or negedge rst) begin
//         if (!rst) begin
//             //reset memory banks
//             integer i;
//             for (i = 0; i < 32; i = i + 1) begin
//                 bank0_mem_real[i] <= 4'b0;
//                 bank0_mem_imag[i] <= 4'b0;
//                 bank1_mem_real[i] <= 4'b0;
//                 bank1_mem_imag[i] <= 4'b0;
//             end
//         end else begin
//             //port 0 write
//             if (wr_en_0) begin
//                 if (write_to_1) begin //if bank_sel is 1 write to bank1
//                     bank1_mem_real[wr_addr_0] <= wr_data_0[3:0];
//                     bank1_mem_imag[wr_addr_0] <= wr_data_0[7:4];
//                 end else begin //if bank_sel is 0 write to bank0
//                     bank0_mem_real[wr_addr_0] <= wr_data_0[3:0];
//                     bank0_mem_imag[wr_addr_0] <= wr_data_0[7:4];
//                 end
//             end

//             //port 1 write
//             if (wr_en_1) begin
//                 if (write_to_1) begin //if bank_sel is 1 write to bank1
//                     bank1_mem_real[wr_addr_1] <= wr_data_1[3:0];
//                     bank1_mem_imag[wr_addr_1] <= wr_data_1[7:4];
//                 end else begin //if bank_sel is 0 write to bank0
//                     bank0_mem_real[wr_addr_1] <= wr_data_1[3:0];
//                     bank0_mem_imag[wr_addr_1] <= wr_data_1[7:4];
//                 end
//             end
//         end
//     end

// endmodule

tb/tb_memory.v
`timescale 1ns / 1ps

module tb_fp4_fft_memory_dff;

    //=== testbench signals ===//
    reg clk;
    reg rst;
    reg bank_sel;
    
    //port 0: read from processing bank
    reg [4:0] rd_addr_0;
    wire [7:0] rd_data_0;
    
    //port 1: write to filling bank
    reg wr_en_1;
    reg [4:0] wr_addr_1;
    reg [7:0] wr_data_1;
    
    //test counters
    integer test_pass_count;
    integer test_fail_count;

    //=== instantiate memory module ===//
    fp4_fft_memory_dff uut (
        .clk(clk),
        .rst(rst),
        .bank_sel(bank_sel),
        .rd_addr_0(rd_addr_0),
        .rd_data_0(rd_data_0),
        .wr_en_1(wr_en_1),
        .wr_addr_1(wr_addr_1),
        .wr_data_1(wr_data_1)
    );

    //=== clock generation (100mhz) ===//
    initial begin
        clk = 0;
        forever #5 clk = ~clk;
    end

    //=== waveform dump ===//
    initial begin
        $dumpfile("tb_fp4_fft_memory_dff.vcd");
        $dumpvars(0, tb_fp4_fft_memory_dff);
    end

    //=== test tasks ===//
    
    //task to write to filling bank
    task write_memory;
        input [4:0] addr;
        input [7:0] data;
        begin
            wr_en_1 = 1;
            wr_addr_1 = addr;
            wr_data_1 = data;
            @(posedge clk);
            #1;
            wr_en_1 = 0;
        end
    endtask

    //task to read from processing bank and verify
    task read_memory;
        input [4:0] addr;
        input [7:0] expected_data;
        begin
            rd_addr_0 = addr;
            @(posedge clk);
            #1;
            if (rd_data_0 === expected_data) begin
                $display("read pass: addr %0d data %0h", addr, rd_data_0);
                test_pass_count = test_pass_count + 1;
            end else begin
                $display("read fail: addr %0d expected %0h got %0h", 
                         addr, expected_data, rd_data_0);
                test_fail_count = test_fail_count + 1;
            end
        end
    endtask

    //=== test sequence ===//
    initial begin
        //initialize counters
        test_pass_count = 0;
        test_fail_count = 0;

        $display("========================================");
        $display("  fp4 fft ping-pong memory testbench");
        $display("========================================");
        $display("clock period: 10ns (100mhz)");
        $display("memory size: 32 x 8-bit per bank");
        $display("========================================\n");

        //test 1: reset memory
        $display("test 1: reset memory");
        rst = 0;
        bank_sel = 0;
        rd_addr_0 = 0;
        wr_en_1 = 0;
        #20;
        rst = 1;
        #20;
        $display("reset complete.\n");

        //test 2: write to bank 0
        $display("test 2: write to bank 0");
        bank_sel = 1; //write to bank 0 (opposite of bank_sel)
        write_memory(5'd0, 8'b01100101);  //addr 0: real=6, imag=5
        #10;
        write_memory(5'd1, 8'b10001001);  //addr 1: real=8, imag=9
        #10;
        write_memory(5'd2, 8'b00110100);  //addr 2: real=3, imag=4
        #10;
        write_memory(5'd3, 8'b11110000);  //addr 3: real=15, imag=0
        #10;
        write_memory(5'd31, 8'b00011110); //addr 31: real=1, imag=14
        #10;
        $display("write operations complete.\n");

        //test 3: read from bank 0
        $display("test 3: read from bank 0");
        bank_sel = 0; //read from bank 0
        read_memory(5'd0, 8'b01100101);  //addr 0
        #5;
        read_memory(5'd1, 8'b10001001);  //addr 1
        #5;
        read_memory(5'd2, 8'b00110100);  //addr 2
        #5;
        read_memory(5'd3, 8'b11110000);  //addr 3
        #5;
        read_memory(5'd31, 8'b00011110); //addr 31
        #5;
        $display("read operations complete.\n");

        //test 4: write to bank 1
        $display("test 4: write to bank 1");
        bank_sel = 0; //write to bank 1 (opposite of bank_sel)
        write_memory(5'd0, 8'b01010110);  //addr 0: real=5, imag=6
        #10;
        write_memory(5'd1, 8'b10011000);  //addr 1: real=9, imag=8
        #10;
        write_memory(5'd2, 8'b01000011);  //addr 2: real=4, imag=3
        #10;
        write_memory(5'd3, 8'b00001111);  //addr 3: real=0, imag=15
        #10;
        write_memory(5'd31, 8'b11100001); //addr 31: real=14, imag=1
        #10;
        $display("write operations complete.\n");

        //test 5: read from bank 1
        $display("test 5: read from bank 1");
        bank_sel = 1; //read from bank 1
        read_memory(5'd0, 8'b01010110);  //addr 0
        #5;
        read_memory(5'd1, 8'b10011000);  //addr 1
        #5;
        read_memory(5'd2, 8'b01000011);  //addr 2
        #5;
        read_memory(5'd3, 8'b00001111);  //addr 3
        #5;
        read_memory(5'd31, 8'b11100001); //addr 31
        #5;
        $display("read operations complete.\n");

        //test 6: ping-pong bank swap test
        $display("test 6: ping-pong bank swap test");
        
        //re-establish known state in bank 0
        bank_sel = 1; //write to bank 0
        write_memory(5'd0, 8'b01100101);  //write to bank 0 addr 0
        #10;
        write_memory(5'd1, 8'b10001001);  //write to bank 0 addr 1
        #10;
        
        //now test ping-pong
        bank_sel = 0; //read from bank 0
        read_memory(5'd0, 8'b01100101);  //read from bank 0
        #5;
        
        bank_sel = 0; //write to bank 1
        write_memory(5'd4, 8'b11111111);  //write to bank 1 addr 4
        #10;
        
        bank_sel = 0; //read from bank 0 again
        read_memory(5'd1, 8'b10001001);  //read from bank 0
        #5;
        
        bank_sel = 0; //write to bank 1
        write_memory(5'd5, 8'b00000000);  //write to bank 1 addr 5
        #10;
        $display("ping-pong operations complete.\n");

        //test 7: simultaneous read-write test
        $display("test 7: simultaneous read-write test");
        
        //ensure bank 0 has expected data
        bank_sel = 1; //write to bank 0
        write_memory(5'd2, 8'b00110100);  //re-write to bank 0 addr 2
        #10;
        write_memory(5'd3, 8'b11110000);  //re-write to bank 0 addr 3
        #10;
        
        //now read from bank 0 while writing to bank 1
        bank_sel = 0; //read from bank 0, write to bank 1
        rd_addr_0 = 5'd2; //set read address
        
        //set up write (will go to bank 1)
        wr_en_1 = 1;
        wr_addr_1 = 5'd6;
        wr_data_1 = 8'b10101010;
        
        @(posedge clk);
        #1;
        wr_en_1 = 0;
        
        //verify read was correct while write happened
        if (rd_data_0 === 8'b00110100) begin
            $display("simultaneous r/w pass: read %0h while writing to other bank", rd_data_0);
            test_pass_count = test_pass_count + 1;
        end else begin
            $display("simultaneous r/w fail: expected %0h got %0h", 8'b00110100, rd_data_0);
            test_fail_count = test_fail_count + 1;
        end
        
        //verify the write to bank 1 worked
        bank_sel = 1; //read from bank 1
        read_memory(5'd6, 8'b10101010);  //should see what we wrote
        #5;

        //final test summary
        $display("========================================");
        $display("test summary:");
        $display("total passed: %0d", test_pass_count);
        $display("total failed: %0d", test_fail_count);
        $display("========================================");
        $finish;
    end

    //timeout to avoid infinite simulation
    initial begin
        #10000;
        $display("testbench timeout: simulation ended after 10000ns.");
        $finish;
    end
endmodule

tb_fp4_fft_memory_dff.vcd
$date
	Thu Dec 11 22:59:33 2025
$end
$version
	Icarus Verilog
$end
$timescale
	1ps
$end
$scope module tb_fp4_fft_memory_dff $end
$var wire 8 ! rd_data_0 [7:0] $end
$var reg 1 " bank_sel $end
$var reg 1 # clk $end
$var reg 5 $ rd_addr_0 [4:0] $end
$var reg 1 % rst $end
$var reg 5 & wr_addr_1 [4:0] $end
$var reg 8 ' wr_data_1 [7:0] $end
$var reg 1 ( wr_en_1 $end
$var integer 32 ) test_fail_count [31:0] $end
$var integer 32 * test_pass_count [31:0] $end
$scope module uut $end
$var wire 1 " bank_sel $end
$var wire 1 # clk $end
$var wire 5 + rd_addr_0 [4:0] $end
$var wire 1 % rst $end
$var wire 5 , wr_addr_1 [4:0] $end
$var wire 8 - wr_data_1 [7:0] $end
$var wire 1 ( wr_en_1 $end
$var wire 8 . rd_data_0 [7:0] $end
$var integer 32 / i [31:0] $end
$upscope $end
$scope task read_memory $end
$var reg 5 0 addr [4:0] $end
$var reg 8 1 expected_data [7:0] $end
$upscope $end
$scope task write_memory $end
$var reg 5 2 addr [4:0] $end
$var reg 8 3 data [7:0] $end
$upscope $end
$upscope $end
$enddefinitions $end
#0
$dumpvars
bx 3
bx 2
bx 1
bx 0
b100000 /
b0 .
bx -
bx ,
b0 +
b0 *
b0 )
0(
bx '
bx &
0%
b0 $
0#
0"
b0 !
$end
#5000
b100000 /
1#
#10000
0#
#15000
b100000 /
1#
#20000
0#
1%
#25000
1#
#30000
0#
#35000
1#
#40000
0#
b1100101 '
b1100101 -
b0 &
b0 ,
1(
b1100101 3
b0 2
1"
#45000
1#
#46000
0(
#50000
0#
#55000
1#
#56000
b10001001 '
b10001001 -
b1 &
b1 ,
1(
b10001001 3
b1 2
#60000
0#
#65000
1#
#66000
0(
#70000
0#
#75000
1#
#76000
b110100 '
b110100 -
b10 &
b10 ,
1(
b110100 3
b10 2
#80000
0#
#85000
1#
#86000
0(
#90000
0#
#95000
1#
#96000
b11110000 '
b11110000 -
b11 &
b11 ,
1(
b11110000 3
b11 2
#100000
0#
#105000
1#
#106000
0(
#110000
0#
#115000
1#
#116000
b11110 '
b11110 -
b11111 &
b11111 ,
1(
b11110 3
b11111 2
#120000
0#
#125000
1#
#126000
0(
#130000
0#
#135000
1#
#136000
b1100101 !
b1100101 .
b1100101 1
b0 0
0"
#140000
0#
#145000
1#
#146000
b1 *
#150000
0#
#151000
b10001001 !
b10001001 .
b1 $
b1 +
b10001001 1
b1 0
#155000
1#
#156000
b10 *
#160000
0#
#161000
b110100 !
b110100 .
b10 $
b10 +
b110100 1
b10 0
#165000
1#
#166000
b11 *
#170000
0#
#171000
b11110000 !
b11110000 .
b11 $
b11 +
b11110000 1
b11 0
#175000
1#
#176000
b100 *
#180000
0#
#181000
b11110 !
b11110 .
b11111 $
b11111 +
b11110 1
b11111 0
#185000
1#
#186000
b101 *
#190000
0#
#191000
b1010110 '
b1010110 -
b0 &
b0 ,
1(
b1010110 3
b0 2
#195000
1#
#196000
0(
#200000
0#
#205000
1#
#206000
b10011000 '
b10011000 -
b1 &
b1 ,
1(
b10011000 3
b1 2
#210000
0#
#215000
1#
#216000
0(
#220000
0#
#225000
1#
#226000
b1000011 '
b1000011 -
b10 &
b10 ,
1(
b1000011 3
b10 2
#230000
0#
#235000
1#
#236000
0(
#240000
0#
#245000
1#
#246000
b1111 '
b1111 -
b11 &
b11 ,
1(
b1111 3
b11 2
#250000
0#
#255000
1#
#256000
0(
#260000
0#
#265000
1#
#266000
b11100001 '
b11100001 -
b11111 &
b11111 ,
1(
b11100001 3
b11111 2
#270000
0#
#275000
1#
#276000
0(
#280000
0#
#285000
1#
#286000
b1010110 !
b1010110 .
b0 $
b0 +
b1010110 1
b0 0
1"
#290000
0#
#295000
1#
#296000
b110 *
#300000
0#
#301000
b10011000 !
b10011000 .
b1 $
b1 +
b10011000 1
b1 0
#305000
1#
#306000
b111 *
#310000
0#
#311000
b1000011 !
b1000011 .
b10 $
b10 +
b1000011 1
b10 0
#315000
1#
#316000
b1000 *
#320000
0#
#321000
b1111 !
b1111 .
b11 $
b11 +
b1111 1
b11 0
#325000
1#
#326000
b1001 *
#330000
0#
#331000
b11100001 !
b11100001 .
b11111 $
b11111 +
b11100001 1
b11111 0
#335000
1#
#336000
b1010 *
#340000
0#
#341000
b1100101 '
b1100101 -
b0 &
b0 ,
1(
b1100101 3
b0 2
#345000
1#
#346000
0(
#350000
0#
#355000
1#
#356000
b10001001 '
b10001001 -
b1 &
b1 ,
1(
b10001001 3
b1 2
#360000
0#
#365000
1#
#366000
0(
#370000
0#
#375000
1#
#376000
b1100101 !
b1100101 .
b0 $
b0 +
b1100101 1
b0 0
0"
#380000
0#
#385000
1#
#386000
b1011 *
#390000
0#
#391000
b11111111 '
b11111111 -
b100 &
b100 ,
1(
b11111111 3
b100 2
#395000
1#
#396000
0(
#400000
0#
#405000
1#
#406000
b10001001 !
b10001001 .
b1 $
b1 +
b10001001 1
b1 0
#410000
0#
#415000
1#
#416000
b1100 *
#420000
0#
#421000
b0 '
b0 -
b101 &
b101 ,
1(
b0 3
b101 2
#425000
1#
#426000
0(
#430000
0#
#435000
1#
#436000
b10011000 !
b10011000 .
b110100 '
b110100 -
b10 &
b10 ,
1(
b110100 3
b10 2
1"
#440000
0#
#445000
1#
#446000
0(
#450000
0#
#455000
1#
#456000
b11110000 '
b11110000 -
b11 &
b11 ,
1(
b11110000 3
b11 2
#460000
0#
#465000
1#
#466000
0(
#470000
0#
#475000
1#
#476000
b110100 !
b110100 .
b10101010 '
b10101010 -
b110 &
b110 ,
1(
b10 $
b10 +
0"
#480000
0#
#485000
1#
#486000
b10101010 !
b10101010 .
b110 $
b110 +
b10101010 1
b110 0
1"
b1101 *
0(
#490000
0#
#495000
1#
#496000
b1110 *
