FP4_E2M1/src/memory_dff.v
// ========================================
// 8-bit D Flip-Flop with Enable
// ========================================
module dff_8bit (
    input wire clk,
    input wire rst,
    input wire en,
    input [7:0] d,
    output reg [7:0] q
);
    always @ (posedge clk or negedge rst) begin
        if (!rst)
            q <= 8'b0;
        else if (en)
            q <= d;
    end
endmodule

// ========================================
// FP4 FFT Memory with Explicit DFF Instantiation
// ========================================
module fp4_fft_memory_dff (
    input wire clk,
    input wire rst,
    input wire bank_sel,
    
    //port 0: read from processing bank
    input wire [4:0] rd_addr_0,
    output wire [7:0] rd_data_0,
    
    //port 1: write to filling bank (ping-pong)
    input wire wr_en_1,
    input wire [4:0] wr_addr_1,
    input wire [7:0] wr_data_1
);

    // Memory Storage: Wire arrays connected to DFF outputs
    wire [7:0] bank0_mem [0:31];
    wire [7:0] bank1_mem [0:31];

    // Generate DFF instances for both banks
    genvar i;
    generate
        for (i = 0; i < 32; i = i + 1) begin : mem_cells
            
            // Bank 0 DFF: Enabled when bank_sel=1 
            // (writing to bank0 when reading from bank1)
            wire bank0_en;
            assign bank0_en = wr_en_1 && (wr_addr_1 == i) && bank_sel;
            
            dff_8bit bank0_dff (
                .clk(clk),
                .rst(rst),
                .en(bank0_en),
                .d(wr_data_1),
                .q(bank0_mem[i])
            );
            
            // Bank 1 DFF: Enabled when bank_sel=0
            // (writing to bank1 when reading from bank0)
            wire bank1_en;
            assign bank1_en = wr_en_1 && (wr_addr_1 == i) && ~bank_sel;
            
            dff_8bit bank1_dff (
                .clk(clk),
                .rst(rst),
                .en(bank1_en),
                .d(wr_data_1),
                .q(bank1_mem[i])
            );
        end
    endgenerate

    //read logic: port 0 reads from same bank as bank_sel
    assign rd_data_0 = bank_sel ? bank1_mem[rd_addr_0] : bank0_mem[rd_addr_0];

endmodule

tb/tb_memory.v
`timescale 1ns / 1ps

module tb_fp4_fft_memory_dff;

    //=== testbench signals ===//
    reg clk;
    reg rst;
    reg bank_sel;
    
    //port 0: read from processing bank
    reg [4:0] rd_addr_0;
    wire [7:0] rd_data_0;
    
    //port 1: write to filling bank
    reg wr_en_1;
    reg [4:0] wr_addr_1;
    reg [7:0] wr_data_1;
    
    //test counters
    integer test_pass_count;
    integer test_fail_count;

    //=== instantiate memory module ===//
    fp4_fft_memory_dff uut (
        .clk(clk),
        .rst(rst),
        .bank_sel(bank_sel),
        .rd_addr_0(rd_addr_0),
        .rd_data_0(rd_data_0),
        .wr_en_1(wr_en_1),
        .wr_addr_1(wr_addr_1),
        .wr_data_1(wr_data_1)
    );

    //=== clock generation (100mhz) ===//
    initial begin
        clk = 0;
        forever #5 clk = ~clk;
    end

    //=== waveform dump ===//
    initial begin
        $dumpfile("tb_fp4_fft_memory_dff.vcd");
        $dumpvars(0, tb_fp4_fft_memory_dff);
    end

    //=== test tasks ===//
    
    //task to write to filling bank
    task write_memory;
        input [4:0] addr;
        input [7:0] data;
        begin
            wr_en_1 = 1;
            wr_addr_1 = addr;
            wr_data_1 = data;
            @(posedge clk);
            #1;
            wr_en_1 = 0;
        end
    endtask

    //task to read from processing bank and verify
    task read_memory;
        input [4:0] addr;
        input [7:0] expected_data;
        begin
            rd_addr_0 = addr;
            @(posedge clk);
            #1;
            if (rd_data_0 === expected_data) begin
                $display("read pass: addr %0d data %0h", addr, rd_data_0);
                test_pass_count = test_pass_count + 1;
            end else begin
                $display("read fail: addr %0d expected %0h got %0h", 
                         addr, expected_data, rd_data_0);
                test_fail_count = test_fail_count + 1;
            end
        end
    endtask

    //=== test sequence ===//
    initial begin
        //initialize counters
        test_pass_count = 0;
        test_fail_count = 0;

        $display("========================================");
        $display("  fp4 fft ping-pong memory testbench");
        $display("========================================");
        $display("clock period: 10ns (100mhz)");
        $display("memory size: 32 x 8-bit per bank");
        $display("========================================\n");

        //test 1: reset memory
        $display("test 1: reset memory");
        rst = 0;
        bank_sel = 0;
        rd_addr_0 = 0;
        wr_en_1 = 0;
        #20;
        rst = 1;
        #20;
        $display("reset complete.\n");

        //test 2: write to bank 0
        $display("test 2: write to bank 0");
        bank_sel = 1; //write to bank 0 (opposite of bank_sel)
        write_memory(5'd0, 8'b01100101);  //addr 0: real=6, imag=5
        #10;
        write_memory(5'd1, 8'b10001001);  //addr 1: real=8, imag=9
        #10;
        write_memory(5'd2, 8'b00110100);  //addr 2: real=3, imag=4
        #10;
        write_memory(5'd3, 8'b11110000);  //addr 3: real=15, imag=0
        #10;
        write_memory(5'd31, 8'b00011110); //addr 31: real=1, imag=14
        #10;
        $display("write operations complete.\n");

        //test 3: read from bank 0
        $display("test 3: read from bank 0");
        bank_sel = 0; //read from bank 0
        read_memory(5'd0, 8'b01100101);  //addr 0
        #5;
        read_memory(5'd1, 8'b10001001);  //addr 1
        #5;
        read_memory(5'd2, 8'b00110100);  //addr 2
        #5;
        read_memory(5'd3, 8'b11110000);  //addr 3
        #5;
        read_memory(5'd31, 8'b00011110); //addr 31
        #5;
        $display("read operations complete.\n");

        //test 4: write to bank 1
        $display("test 4: write to bank 1");
        bank_sel = 0; //write to bank 1 (opposite of bank_sel)
        write_memory(5'd0, 8'b01010110);  //addr 0: real=5, imag=6
        #10;
        write_memory(5'd1, 8'b10011000);  //addr 1: real=9, imag=8
        #10;
        write_memory(5'd2, 8'b01000011);  //addr 2: real=4, imag=3
        #10;
        write_memory(5'd3, 8'b00001111);  //addr 3: real=0, imag=15
        #10;
        write_memory(5'd31, 8'b11100001); //addr 31: real=14, imag=1
        #10;
        $display("write operations complete.\n");

        //test 5: read from bank 1
        $display("test 5: read from bank 1");
        bank_sel = 1; //read from bank 1
        read_memory(5'd0, 8'b01010110);  //addr 0
        #5;
        read_memory(5'd1, 8'b10011000);  //addr 1
        #5;
        read_memory(5'd2, 8'b01000011);  //addr 2
        #5;
        read_memory(5'd3, 8'b00001111);  //addr 3
        #5;
        read_memory(5'd31, 8'b11100001); //addr 31
        #5;
        $display("read operations complete.\n");

        //test 6: ping-pong bank swap test
        $display("test 6: ping-pong bank swap test");
        
        //re-establish known state in bank 0
        bank_sel = 1; //write to bank 0
        write_memory(5'd0, 8'b01100101);  //write to bank 0 addr 0
        #10;
        write_memory(5'd1, 8'b10001001);  //write to bank 0 addr 1
        #10;
        
        //now test ping-pong
        bank_sel = 0; //read from bank 0
        read_memory(5'd0, 8'b01100101);  //read from bank 0
        #5;
        
        bank_sel = 0; //write to bank 1
        write_memory(5'd4, 8'b11111111);  //write to bank 1 addr 4
        #10;
        
        bank_sel = 0; //read from bank 0 again
        read_memory(5'd1, 8'b10001001);  //read from bank 0
        #5;
        
        bank_sel = 0; //write to bank 1
        write_memory(5'd5, 8'b00000000);  //write to bank 1 addr 5
        #10;
        $display("ping-pong operations complete.\n");

        //test 7: simultaneous read-write test
        $display("test 7: simultaneous read-write test");
        
        //ensure bank 0 has expected data
        bank_sel = 1; //write to bank 0
        write_memory(5'd2, 8'b00110100);  //re-write to bank 0 addr 2
        #10;
        write_memory(5'd3, 8'b11110000);  //re-write to bank 0 addr 3
        #10;
        
        //now read from bank 0 while writing to bank 1
        bank_sel = 0; //read from bank 0, write to bank 1
        rd_addr_0 = 5'd2; //set read address
        
        //set up write (will go to bank 1)
        wr_en_1 = 1;
        wr_addr_1 = 5'd6;
        wr_data_1 = 8'b10101010;
        
        @(posedge clk);
        #1;
        wr_en_1 = 0;
        
        //verify read was correct while write happened
        if (rd_data_0 === 8'b00110100) begin
            $display("simultaneous r/w pass: read %0h while writing to other bank", rd_data_0);
            test_pass_count = test_pass_count + 1;
        end else begin
            $display("simultaneous r/w fail: expected %0h got %0h", 8'b00110100, rd_data_0);
            test_fail_count = test_fail_count + 1;
        end
        
        //verify the write to bank 1 worked
        bank_sel = 1; //read from bank 1
        read_memory(5'd6, 8'b10101010);  //should see what we wrote
        #5;

        //final test summary
        $display("========================================");
        $display("test summary:");
        $display("total passed: %0d", test_pass_count);
        $display("total failed: %0d", test_fail_count);
        $display("========================================");
        $finish;
    end

    //timeout to avoid infinite simulation
    initial begin
        #10000;
        $display("testbench timeout: simulation ended after 10000ns.");
        $finish;
    end
endmodule

FP4_E2M1/tb_fp4_fft_memory_dff.vcd
$date
	Sat Dec 13 17:01:51 2025
$end
$version
	Icarus Verilog
$end
$timescale
	1ps
$end
$scope module tb_fp4_fft_memory_dff $end
$var wire 8 ! rd_data_0 [7:0] $end
$var reg 1 " bank_sel $end
$var reg 1 # clk $end
$var reg 5 $ rd_addr_0 [4:0] $end
$var reg 1 % rst $end
$var reg 5 & wr_addr_1 [4:0] $end
$var reg 8 ' wr_data_1 [7:0] $end
$var reg 1 ( wr_en_1 $end
$var integer 32 ) test_fail_count [31:0] $end
$var integer 32 * test_pass_count [31:0] $end
$scope module uut $end
$var wire 1 " bank_sel $end
$var wire 1 # clk $end
$var wire 5 + rd_addr_0 [4:0] $end
$var wire 1 % rst $end
$var wire 5 , wr_addr_1 [4:0] $end
$var wire 8 - wr_data_1 [7:0] $end
$var wire 1 ( wr_en_1 $end
$var wire 8 . rd_data_0 [7:0] $end
$scope begin mem_cells[0] $end
$var wire 1 / bank0_en $end
$var wire 1 0 bank1_en $end
$scope module bank0_dff $end
$var wire 1 # clk $end
$var wire 8 1 d [7:0] $end
$var wire 1 / en $end
$var wire 1 % rst $end
$var reg 8 2 q [7:0] $end
$upscope $end
$scope module bank1_dff $end
$var wire 1 # clk $end
$var wire 8 3 d [7:0] $end
$var wire 1 0 en $end
$var wire 1 % rst $end
$var reg 8 4 q [7:0] $end
$upscope $end
$upscope $end
$scope begin mem_cells[1] $end
$var wire 1 5 bank0_en $end
$var wire 1 6 bank1_en $end
$scope module bank0_dff $end
$var wire 1 # clk $end
$var wire 8 7 d [7:0] $end
$var wire 1 5 en $end
$var wire 1 % rst $end
$var reg 8 8 q [7:0] $end
$upscope $end
$scope module bank1_dff $end
$var wire 1 # clk $end
$var wire 8 9 d [7:0] $end
$var wire 1 6 en $end
$var wire 1 % rst $end
$var reg 8 : q [7:0] $end
$upscope $end
$upscope $end
$scope begin mem_cells[2] $end
$var wire 1 ; bank0_en $end
$var wire 1 < bank1_en $end
$scope module bank0_dff $end
$var wire 1 # clk $end
$var wire 8 = d [7:0] $end
$var wire 1 ; en $end
$var wire 1 % rst $end
$var reg 8 > q [7:0] $end
$upscope $end
$scope module bank1_dff $end
$var wire 1 # clk $end
$var wire 8 ? d [7:0] $end
$var wire 1 < en $end
$var wire 1 % rst $end
$var reg 8 @ q [7:0] $end
$upscope $end
$upscope $end
$scope begin mem_cells[3] $end
$var wire 1 A bank0_en $end
$var wire 1 B bank1_en $end
$scope module bank0_dff $end
$var wire 1 # clk $end
$var wire 8 C d [7:0] $end
$var wire 1 A en $end
$var wire 1 % rst $end
$var reg 8 D q [7:0] $end
$upscope $end
$scope module bank1_dff $end
$var wire 1 # clk $end
$var wire 8 E d [7:0] $end
$var wire 1 B en $end
$var wire 1 % rst $end
$var reg 8 F q [7:0] $end
$upscope $end
$upscope $end
$scope begin mem_cells[4] $end
$var wire 1 G bank0_en $end
$var wire 1 H bank1_en $end
$scope module bank0_dff $end
$var wire 1 # clk $end
$var wire 8 I d [7:0] $end
$var wire 1 G en $end
$var wire 1 % rst $end
$var reg 8 J q [7:0] $end
$upscope $end
$scope module bank1_dff $end
$var wire 1 # clk $end
$var wire 8 K d [7:0] $end
$var wire 1 H en $end
$var wire 1 % rst $end
$var reg 8 L q [7:0] $end
$upscope $end
$upscope $end
$scope begin mem_cells[5] $end
$var wire 1 M bank0_en $end
$var wire 1 N bank1_en $end
$scope module bank0_dff $end
$var wire 1 # clk $end
$var wire 8 O d [7:0] $end
$var wire 1 M en $end
$var wire 1 % rst $end
$var reg 8 P q [7:0] $end
$upscope $end
$scope module bank1_dff $end
$var wire 1 # clk $end
$var wire 8 Q d [7:0] $end
$var wire 1 N en $end
$var wire 1 % rst $end
$var reg 8 R q [7:0] $end
$upscope $end
$upscope $end
$scope begin mem_cells[6] $end
$var wire 1 S bank0_en $end
$var wire 1 T bank1_en $end
$scope module bank0_dff $end
$var wire 1 # clk $end
$var wire 8 U d [7:0] $end
$var wire 1 S en $end
$var wire 1 % rst $end
$var reg 8 V q [7:0] $end
$upscope $end
$scope module bank1_dff $end
$var wire 1 # clk $end
$var wire 8 W d [7:0] $end
$var wire 1 T en $end
$var wire 1 % rst $end
$var reg 8 X q [7:0] $end
$upscope $end
$upscope $end
$scope begin mem_cells[7] $end
$var wire 1 Y bank0_en $end
$var wire 1 Z bank1_en $end
$scope module bank0_dff $end
$var wire 1 # clk $end
$var wire 8 [ d [7:0] $end
$var wire 1 Y en $end
$var wire 1 % rst $end
$var reg 8 \ q [7:0] $end
$upscope $end
$scope module bank1_dff $end
$var wire 1 # clk $end
$var wire 8 ] d [7:0] $end
$var wire 1 Z en $end
$var wire 1 % rst $end
$var reg 8 ^ q [7:0] $end
$upscope $end
$upscope $end
$scope begin mem_cells[8] $end
$var wire 1 _ bank0_en $end
$var wire 1 ` bank1_en $end
$scope module bank0_dff $end
$var wire 1 # clk $end
$var wire 8 a d [7:0] $end
$var wire 1 _ en $end
$var wire 1 % rst $end
$var reg 8 b q [7:0] $end
$upscope $end
$scope module bank1_dff $end
$var wire 1 # clk $end
$var wire 8 c d [7:0] $end
$var wire 1 ` en $end
$var wire 1 % rst $end
$var reg 8 d q [7:0] $end
$upscope $end
$upscope $end
$scope begin mem_cells[9] $end
$var wire 1 e bank0_en $end
$var wire 1 f bank1_en $end
$scope module bank0_dff $end
$var wire 1 # clk $end
$var wire 8 g d [7:0] $end
$var wire 1 e en $end
$var wire 1 % rst $end
$var reg 8 h q [7:0] $end
$upscope $end
$scope module bank1_dff $end
$var wire 1 # clk $end
$var wire 8 i d [7:0] $end
$var wire 1 f en $end
$var wire 1 % rst $end
$var reg 8 j q [7:0] $end
$upscope $end
$upscope $end
$scope begin mem_cells[10] $end
$var wire 1 k bank0_en $end
$var wire 1 l bank1_en $end
$scope module bank0_dff $end
$var wire 1 # clk $end
$var wire 8 m d [7:0] $end
$var wire 1 k en $end
$var wire 1 % rst $end
$var reg 8 n q [7:0] $end
$upscope $end
$scope module bank1_dff $end
$var wire 1 # clk $end
$var wire 8 o d [7:0] $end
$var wire 1 l en $end
$var wire 1 % rst $end
$var reg 8 p q [7:0] $end
$upscope $end
$upscope $end
$scope begin mem_cells[11] $end
$var wire 1 q bank0_en $end
$var wire 1 r bank1_en $end
$scope module bank0_dff $end
$var wire 1 # clk $end
$var wire 8 s d [7:0] $end
$var wire 1 q en $end
$var wire 1 % rst $end
$var reg 8 t q [7:0] $end
$upscope $end
$scope module bank1_dff $end
$var wire 1 # clk $end
$var wire 8 u d [7:0] $end
$var wire 1 r en $end
$var wire 1 % rst $end
$var reg 8 v q [7:0] $end
$upscope $end
$upscope $end
$scope begin mem_cells[12] $end
$var wire 1 w bank0_en $end
$var wire 1 x bank1_en $end
$scope module bank0_dff $end
$var wire 1 # clk $end
$var wire 8 y d [7:0] $end
$var wire 1 w en $end
$var wire 1 % rst $end
$var reg 8 z q [7:0] $end
$upscope $end
$scope module bank1_dff $end
$var wire 1 # clk $end
$var wire 8 { d [7:0] $end
$var wire 1 x en $end
$var wire 1 % rst $end
$var reg 8 | q [7:0] $end
$upscope $end
$upscope $end
$scope begin mem_cells[13] $end
$var wire 1 } bank0_en $end
$var wire 1 ~ bank1_en $end
$scope module bank0_dff $end
$var wire 1 # clk $end
$var wire 8 !" d [7:0] $end
$var wire 1 } en $end
$var wire 1 % rst $end
$var reg 8 "" q [7:0] $end
$upscope $end
$scope module bank1_dff $end
$var wire 1 # clk $end
$var wire 8 #" d [7:0] $end
$var wire 1 ~ en $end
$var wire 1 % rst $end
$var reg 8 $" q [7:0] $end
$upscope $end
$upscope $end
$scope begin mem_cells[14] $end
$var wire 1 %" bank0_en $end
$var wire 1 &" bank1_en $end
$scope module bank0_dff $end
$var wire 1 # clk $end
$var wire 8 '" d [7:0] $end
$var wire 1 %" en $end
$var wire 1 % rst $end
$var reg 8 (" q [7:0] $end
$upscope $end
$scope module bank1_dff $end
$var wire 1 # clk $end
$var wire 8 )" d [7:0] $end
$var wire 1 &" en $end
$var wire 1 % rst $end
$var reg 8 *" q [7:0] $end
$upscope $end
$upscope $end
$scope begin mem_cells[15] $end
$var wire 1 +" bank0_en $end
$var wire 1 ," bank1_en $end
$scope module bank0_dff $end
$var wire 1 # clk $end
$var wire 8 -" d [7:0] $end
$var wire 1 +" en $end
$var wire 1 % rst $end
$var reg 8 ." q [7:0] $end
$upscope $end
$scope module bank1_dff $end
$var wire 1 # clk $end
$var wire 8 /" d [7:0] $end
$var wire 1 ," en $end
$var wire 1 % rst $end
$var reg 8 0" q [7:0] $end
$upscope $end
$upscope $end
$scope begin mem_cells[16] $end
$var wire 1 1" bank0_en $end
$var wire 1 2" bank1_en $end
$scope module bank0_dff $end
$var wire 1 # clk $end
$var wire 8 3" d [7:0] $end
$var wire 1 1" en $end
$var wire 1 % rst $end
$var reg 8 4" q [7:0] $end
$upscope $end
$scope module bank1_dff $end
$var wire 1 # clk $end
$var wire 8 5" d [7:0] $end
$var wire 1 2" en $end
$var wire 1 % rst $end
$var reg 8 6" q [7:0] $end
$upscope $end
$upscope $end
$scope begin mem_cells[17] $end
$var wire 1 7" bank0_en $end
$var wire 1 8" bank1_en $end
$scope module bank0_dff $end
$var wire 1 # clk $end
$var wire 8 9" d [7:0] $end
$var wire 1 7" en $end
$var wire 1 % rst $end
$var reg 8 :" q [7:0] $end
$upscope $end
$scope module bank1_dff $end
$var wire 1 # clk $end
$var wire 8 ;" d [7:0] $end
$var wire 1 8" en $end
$var wire 1 % rst $end
$var reg 8 <" q [7:0] $end
$upscope $end
$upscope $end
$scope begin mem_cells[18] $end
$var wire 1 =" bank0_en $end
$var wire 1 >" bank1_en $end
$scope module bank0_dff $end
$var wire 1 # clk $end
$var wire 8 ?" d [7:0] $end
$var wire 1 =" en $end
$var wire 1 % rst $end
$var reg 8 @" q [7:0] $end
$upscope $end
$scope module bank1_dff $end
$var wire 1 # clk $end
$var wire 8 A" d [7:0] $end
$var wire 1 >" en $end
$var wire 1 % rst $end
$var reg 8 B" q [7:0] $end
$upscope $end
$upscope $end
$scope begin mem_cells[19] $end
$var wire 1 C" bank0_en $end
$var wire 1 D" bank1_en $end
$scope module bank0_dff $end
$var wire 1 # clk $end
$var wire 8 E" d [7:0] $end
$var wire 1 C" en $end
$var wire 1 % rst $end
$var reg 8 F" q [7:0] $end
$upscope $end
$scope module bank1_dff $end
$var wire 1 # clk $end
$var wire 8 G" d [7:0] $end
$var wire 1 D" en $end
$var wire 1 % rst $end
$var reg 8 H" q [7:0] $end
$upscope $end
$upscope $end
$scope begin mem_cells[20] $end
$var wire 1 I" bank0_en $end
$var wire 1 J" bank1_en $end
$scope module bank0_dff $end
$var wire 1 # clk $end
$var wire 8 K" d [7:0] $end
$var wire 1 I" en $end
$var wire 1 % rst $end
$var reg 8 L" q [7:0] $end
$upscope $end
$scope module bank1_dff $end
$var wire 1 # clk $end
$var wire 8 M" d [7:0] $end
$var wire 1 J" en $end
$var wire 1 % rst $end
$var reg 8 N" q [7:0] $end
$upscope $end
$upscope $end
$scope begin mem_cells[21] $end
$var wire 1 O" bank0_en $end
$var wire 1 P" bank1_en $end
$scope module bank0_dff $end
$var wire 1 # clk $end
$var wire 8 Q" d [7:0] $end
$var wire 1 O" en $end
$var wire 1 % rst $end
$var reg 8 R" q [7:0] $end
$upscope $end
$scope module bank1_dff $end
$var wire 1 # clk $end
$var wire 8 S" d [7:0] $end
$var wire 1 P" en $end
$var wire 1 % rst $end
$var reg 8 T" q [7:0] $end
$upscope $end
$upscope $end
$scope begin mem_cells[22] $end
$var wire 1 U" bank0_en $end
$var wire 1 V" bank1_en $end
$scope module bank0_dff $end
$var wire 1 # clk $end
$var wire 8 W" d [7:0] $end
$var wire 1 U" en $end
$var wire 1 % rst $end
$var reg 8 X" q [7:0] $end
$upscope $end
$scope module bank1_dff $end
$var wire 1 # clk $end
$var wire 8 Y" d [7:0] $end
$var wire 1 V" en $end
$var wire 1 % rst $end
$var reg 8 Z" q [7:0] $end
$upscope $end
$upscope $end
$scope begin mem_cells[23] $end
$var wire 1 [" bank0_en $end
$var wire 1 \" bank1_en $end
$scope module bank0_dff $end
$var wire 1 # clk $end
$var wire 8 ]" d [7:0] $end
$var wire 1 [" en $end
$var wire 1 % rst $end
$var reg 8 ^" q [7:0] $end
$upscope $end
$scope module bank1_dff $end
$var wire 1 # clk $end
$var wire 8 _" d [7:0] $end
$var wire 1 \" en $end
$var wire 1 % rst $end
$var reg 8 `" q [7:0] $end
$upscope $end
$upscope $end
$scope begin mem_cells[24] $end
$var wire 1 a" bank0_en $end
$var wire 1 b" bank1_en $end
$scope module bank0_dff $end
$var wire 1 # clk $end
$var wire 8 c" d [7:0] $end
$var wire 1 a" en $end
$var wire 1 % rst $end
$var reg 8 d" q [7:0] $end
$upscope $end
$scope module bank1_dff $end
$var wire 1 # clk $end
$var wire 8 e" d [7:0] $end
$var wire 1 b" en $end
$var wire 1 % rst $end
$var reg 8 f" q [7:0] $end
$upscope $end
$upscope $end
$scope begin mem_cells[25] $end
$var wire 1 g" bank0_en $end
$var wire 1 h" bank1_en $end
$scope module bank0_dff $end
$var wire 1 # clk $end
$var wire 8 i" d [7:0] $end
$var wire 1 g" en $end
$var wire 1 % rst $end
$var reg 8 j" q [7:0] $end
$upscope $end
$scope module bank1_dff $end
$var wire 1 # clk $end
$var wire 8 k" d [7:0] $end
$var wire 1 h" en $end
$var wire 1 % rst $end
$var reg 8 l" q [7:0] $end
$upscope $end
$upscope $end
$scope begin mem_cells[26] $end
$var wire 1 m" bank0_en $end
$var wire 1 n" bank1_en $end
$scope module bank0_dff $end
$var wire 1 # clk $end
$var wire 8 o" d [7:0] $end
$var wire 1 m" en $end
$var wire 1 % rst $end
$var reg 8 p" q [7:0] $end
$upscope $end
$scope module bank1_dff $end
$var wire 1 # clk $end
$var wire 8 q" d [7:0] $end
$var wire 1 n" en $end
$var wire 1 % rst $end
$var reg 8 r" q [7:0] $end
$upscope $end
$upscope $end
$scope begin mem_cells[27] $end
$var wire 1 s" bank0_en $end
$var wire 1 t" bank1_en $end
$scope module bank0_dff $end
$var wire 1 # clk $end
$var wire 8 u" d [7:0] $end
$var wire 1 s" en $end
$var wire 1 % rst $end
$var reg 8 v" q [7:0] $end
$upscope $end
$scope module bank1_dff $end
$var wire 1 # clk $end
$var wire 8 w" d [7:0] $end
$var wire 1 t" en $end
$var wire 1 % rst $end
$var reg 8 x" q [7:0] $end
$upscope $end
$upscope $end
$scope begin mem_cells[28] $end
$var wire 1 y" bank0_en $end
$var wire 1 z" bank1_en $end
$scope module bank0_dff $end
$var wire 1 # clk $end
$var wire 8 {" d [7:0] $end
$var wire 1 y" en $end
$var wire 1 % rst $end
$var reg 8 |" q [7:0] $end
$upscope $end
$scope module bank1_dff $end
$var wire 1 # clk $end
$var wire 8 }" d [7:0] $end
$var wire 1 z" en $end
$var wire 1 % rst $end
$var reg 8 ~" q [7:0] $end
$upscope $end
$upscope $end
$scope begin mem_cells[29] $end
$var wire 1 !# bank0_en $end
$var wire 1 "# bank1_en $end
$scope module bank0_dff $end
$var wire 1 # clk $end
$var wire 8 ## d [7:0] $end
$var wire 1 !# en $end
$var wire 1 % rst $end
$var reg 8 $# q [7:0] $end
$upscope $end
$scope module bank1_dff $end
$var wire 1 # clk $end
$var wire 8 %# d [7:0] $end
$var wire 1 "# en $end
$var wire 1 % rst $end
$var reg 8 &# q [7:0] $end
$upscope $end
$upscope $end
$scope begin mem_cells[30] $end
$var wire 1 '# bank0_en $end
$var wire 1 (# bank1_en $end
$scope module bank0_dff $end
$var wire 1 # clk $end
$var wire 8 )# d [7:0] $end
$var wire 1 '# en $end
$var wire 1 % rst $end
$var reg 8 *# q [7:0] $end
$upscope $end
$scope module bank1_dff $end
$var wire 1 # clk $end
$var wire 8 +# d [7:0] $end
$var wire 1 (# en $end
$var wire 1 % rst $end
$var reg 8 ,# q [7:0] $end
$upscope $end
$upscope $end
$scope begin mem_cells[31] $end
$var wire 1 -# bank0_en $end
$var wire 1 .# bank1_en $end
$scope module bank0_dff $end
$var wire 1 # clk $end
$var wire 8 /# d [7:0] $end
$var wire 1 -# en $end
$var wire 1 % rst $end
$var reg 8 0# q [7:0] $end
$upscope $end
$scope module bank1_dff $end
$var wire 1 # clk $end
$var wire 8 1# d [7:0] $end
$var wire 1 .# en $end
$var wire 1 % rst $end
$var reg 8 2# q [7:0] $end
$upscope $end
$upscope $end
$upscope $end
$scope task read_memory $end
$var reg 5 3# addr [4:0] $end
$var reg 8 4# expected_data [7:0] $end
$upscope $end
$scope task write_memory $end
$var reg 5 5# addr [4:0] $end
$var reg 8 6# data [7:0] $end
$upscope $end
$upscope $end
$enddefinitions $end
#0
$dumpvars
bx 6#
bx 5#
bx 4#
bx 3#
b0 2#
bx 1#
b0 0#
bx /#
0.#
0-#
b0 ,#
bx +#
b0 *#
bx )#
0(#
0'#
b0 &#
bx %#
b0 $#
bx ##
0"#
0!#
b0 ~"
bx }"
b0 |"
bx {"
0z"
0y"
b0 x"
bx w"
b0 v"
bx u"
0t"
0s"
b0 r"
bx q"
b0 p"
bx o"
0n"
0m"
b0 l"
bx k"
b0 j"
bx i"
0h"
0g"
b0 f"
bx e"
b0 d"
bx c"
0b"
0a"
b0 `"
bx _"
b0 ^"
bx ]"
0\"
0["
b0 Z"
bx Y"
b0 X"
bx W"
0V"
0U"
b0 T"
bx S"
b0 R"
bx Q"
0P"
0O"
b0 N"
bx M"
b0 L"
bx K"
0J"
0I"
b0 H"
bx G"
b0 F"
bx E"
0D"
0C"
b0 B"
bx A"
b0 @"
bx ?"
0>"
0="
b0 <"
bx ;"
b0 :"
bx 9"
08"
07"
b0 6"
bx 5"
b0 4"
bx 3"
02"
01"
b0 0"
bx /"
b0 ."
bx -"
0,"
0+"
b0 *"
bx )"
b0 ("
bx '"
0&"
0%"
b0 $"
bx #"
b0 ""
bx !"
0~
0}
b0 |
bx {
b0 z
bx y
0x
0w
b0 v
bx u
b0 t
bx s
0r
0q
b0 p
bx o
b0 n
bx m
0l
0k
b0 j
bx i
b0 h
bx g
0f
0e
b0 d
bx c
b0 b
bx a
0`
0_
b0 ^
bx ]
b0 \
bx [
0Z
0Y
b0 X
bx W
b0 V
bx U
0T
0S
b0 R
bx Q
b0 P
bx O
0N
0M
b0 L
bx K
b0 J
bx I
0H
0G
b0 F
bx E
b0 D
bx C
0B
0A
b0 @
bx ?
b0 >
bx =
0<
0;
b0 :
bx 9
b0 8
bx 7
06
05
b0 4
bx 3
b0 2
bx 1
00
0/
b0 .
bx -
bx ,
b0 +
b0 *
b0 )
0(
bx '
bx &
0%
b0 $
0#
0"
b0 !
$end
#5000
1#
#10000
0#
#15000
1#
#20000
0#
1%
#25000
1#
#30000
0#
#35000
1#
#40000
1/
0#
b1100101 '
b1100101 -
b1100101 1
b1100101 3
b1100101 7
b1100101 9
b1100101 =
b1100101 ?
b1100101 C
b1100101 E
b1100101 I
b1100101 K
b1100101 O
b1100101 Q
b1100101 U
b1100101 W
b1100101 [
b1100101 ]
b1100101 a
b1100101 c
b1100101 g
b1100101 i
b1100101 m
b1100101 o
b1100101 s
b1100101 u
b1100101 y
b1100101 {
b1100101 !"
b1100101 #"
b1100101 '"
b1100101 )"
b1100101 -"
b1100101 /"
b1100101 3"
b1100101 5"
b1100101 9"
b1100101 ;"
b1100101 ?"
b1100101 A"
b1100101 E"
b1100101 G"
b1100101 K"
b1100101 M"
b1100101 Q"
b1100101 S"
b1100101 W"
b1100101 Y"
b1100101 ]"
b1100101 _"
b1100101 c"
b1100101 e"
b1100101 i"
b1100101 k"
b1100101 o"
b1100101 q"
b1100101 u"
b1100101 w"
b1100101 {"
b1100101 }"
b1100101 ##
b1100101 %#
b1100101 )#
b1100101 +#
b1100101 /#
b1100101 1#
b0 &
b0 ,
1(
b1100101 6#
b0 5#
1"
#45000
b1100101 2
1#
#46000
0/
0(
#50000
0#
#55000
1#
#56000
15
b10001001 '
b10001001 -
b10001001 1
b10001001 3
b10001001 7
b10001001 9
b10001001 =
b10001001 ?
b10001001 C
b10001001 E
b10001001 I
b10001001 K
b10001001 O
b10001001 Q
b10001001 U
b10001001 W
b10001001 [
b10001001 ]
b10001001 a
b10001001 c
b10001001 g
b10001001 i
b10001001 m
b10001001 o
b10001001 s
b10001001 u
b10001001 y
b10001001 {
b10001001 !"
b10001001 #"
b10001001 '"
b10001001 )"
b10001001 -"
b10001001 /"
b10001001 3"
b10001001 5"
b10001001 9"
b10001001 ;"
b10001001 ?"
b10001001 A"
b10001001 E"
b10001001 G"
b10001001 K"
b10001001 M"
b10001001 Q"
b10001001 S"
b10001001 W"
b10001001 Y"
b10001001 ]"
b10001001 _"
b10001001 c"
b10001001 e"
b10001001 i"
b10001001 k"
b10001001 o"
b10001001 q"
b10001001 u"
b10001001 w"
b10001001 {"
b10001001 }"
b10001001 ##
b10001001 %#
b10001001 )#
b10001001 +#
b10001001 /#
b10001001 1#
b1 &
b1 ,
1(
b10001001 6#
b1 5#
#60000
0#
#65000
b10001001 8
1#
#66000
05
0(
#70000
0#
#75000
1#
